README.rst
setup.py
GenThemAll.egg-info/PKG-INFO
GenThemAll.egg-info/SOURCES.txt
GenThemAll.egg-info/dependency_links.txt
GenThemAll.egg-info/entry_points.txt
GenThemAll.egg-info/requires.txt
GenThemAll.egg-info/top_level.txt
genthemall/__init__.py
genthemall/commands.py
genthemall/conf.py
genthemall/core.py
genthemall/main.py
genthemall/utils.py
tests/__init__.py
tests/test_core.py
tests/test_main.py
tests/test_utils.py