Metadata-Version: 1.1
Name: GenThemAll
Version: 0.3.0
Summary: GenThemAll is a simple, Pythonic tool for genernate code and whatevery you want.
Home-page: https://github.com/donilan/python-genthemall
Author: Doni
Author-email: d@ii2d.com
License: Apache License, Version 2.0
Platform: UNKNOWN
Classifier: Environment :: Console
Classifier: Programming Language :: Python :: 2.7
Classifier: License :: OSI Approved :: Apache Software License
